gillions/__init__.py
gillions/__main__.py
gillions/handler.py
gillions/command/__init__.py
gillions/command/null_command.py
gillions-0.0.2.dist-info/METADATA
gillions-0.0.2.dist-info/WHEEL
gillions-0.0.2.dist-info/entry_points.txt
gillions-0.0.2.dist-info/top_level.txt
gillions-0.0.2.dist-info/RECORD
