Metadata-Version: 2.1
Name: gillions
Version: 0.0.2
Summary: Placeholder for a personal accounting system
Author-email: Francis Potter <gillions@steampunkwizard.ca>
License: MIT
Requires-Python: >=3.10
Requires-Dist: wizlib (>=0.8.4)
